slapdash/__init__.py
slapdash/client.py
slapdash/decorators.py
slapdash/examples/async.py
slapdash/examples/client_example.py
slapdash/examples/custom_css.css
slapdash/examples/custom_css.py
slapdash/examples/dac_example.py
slapdash/examples/datastream_example.py
slapdash/examples/device_example.py
slapdash/examples/doc_example.py
slapdash/examples/enum_example.py
slapdash/examples/example.py
slapdash/examples/hello_world.py
slapdash/examples/metadata_example.py
slapdash/examples/readonly_example.py
slapdash/examples/refresh_example.py
slapdash/examples/saver_example.py
slapdash/examples/settings.json
slapdash/examples/simple.py
slapdash/examples/slider_example.py
slapdash/examples/subcomponents.py
slapdash/examples/trigger_update_example.py
slapdash/examples.py
slapdash/frontend/custom.css
slapdash/frontend/custom.js
slapdash/frontend/dashboard.css
slapdash/frontend/index.css
slapdash/frontend/index.html
slapdash/frontend/index.js
slapdash/frontend/package-lock.json
slapdash/main.py
slapdash/metadata.py
slapdash/model.py
slapdash/testing.py
slapdash/types.py
slapdash/version.json
slapdash/version.py
slapdash/web.py
slapdash-1.0.3.dist-info/METADATA
slapdash-1.0.3.dist-info/WHEEL
slapdash-1.0.3.dist-info/RECORD
