Metadata-Version: 2.1
Name: slapdash
Version: 1.0.3
Summary: Create device and application control dashboards instantly
Author: Matt Grau
Author-email: graum@phys.ethz.ch
Requires-Python: >=3.7,<4.0
Classifier: Programming Language :: Python :: 3
Classifier: Programming Language :: Python :: 3.7
Classifier: Programming Language :: Python :: 3.8
Classifier: Programming Language :: Python :: 3.9
Classifier: Programming Language :: Python :: 3.10
Classifier: Programming Language :: Python :: 3.11
Classifier: Programming Language :: Python :: 3.12
Provides-Extra: examples
Requires-Dist: aiofiles (>=22.1.0,<23.0.0)
Requires-Dist: fastapi (>=0.88.0,<0.89.0)
Requires-Dist: matplotlib ; extra == "examples"
Requires-Dist: python-socketio (>=4.6.1,<5.0.0)
Requires-Dist: requests (>=2.28.1,<3.0.0)
Requires-Dist: uvicorn (>=0.20.0,<0.21.0)
Requires-Dist: websockets (>=10.4,<11.0)
